{"cameraMode":{"drawMode":0,"name":"Shaded","section":"Shading Mode"},"sceneLighting":false,"audioPlay":false,"sceneViewState":{"m_AlwaysRefresh":false,"showFog":true,"showSkybox":false,"showFlares":true,"showImageEffects":true,"showParticleSystems":true,"showVisualEffectGraphs":true,"m_FxEnabled":true},"in2DMode":false,"pivot":{"x":-3.7977066040039064,"y":1.2516741752624512,"z":-0.04347654804587364},"rotation":{"x":0.23677554726600648,"y":-0.43495383858680727,"z":0.11966034024953842,"w":0.8605244755744934},"size":6.4594268798828129,"orthographic":false}